lockprompt/__init__.py
lockprompt-1.1.2.dist-info/METADATA
lockprompt-1.1.2.dist-info/WHEEL
lockprompt-1.1.2.dist-info/top_level.txt
lockprompt-1.1.2.dist-info/RECORD
