Metadata-Version: 2.4
Name: lockprompt
Version: 1.1.2
Summary: Lightweight safety layer to scan prompts and LLM outputs via external API.
Author: David Willis-Owen
Author-email: david@willis-owen.com
Requires-Python: >=3.7
Requires-Dist: requests
Dynamic: author
Dynamic: author-email
Dynamic: description
Dynamic: description-content-type
Dynamic: requires-dist
Dynamic: requires-python
Dynamic: summary
